
{
"cloths" : [
        {"cloth":"p","color":"blue","gender":"man","size":"small"},
        {"cloth":"t","color":"yellow","gender":"woman","size":"big"},
        {"cloth":"s","color":"blue","gender":"man","size":"small"},
        {"cloth":"t","color":"yellow","gender":"woman","size":"medium"},
        {"cloth":"p","color":"pink","gender":"man","size":"big"},
        {"cloth":"p","color":"blue","gender":"woman","size":"medium"},
        {"cloth":"s","color":"pink","gender":"man","size":"small"},
        {"cloth":"t","color":"yellow","gender":"woman","size":"big"},
        {"cloth":"t","color":"blue","gender":"man","size":"big"},
        {"cloth":"s","color":"pink","gender":"woman","size":"big"},
        {"cloth":"p","color":"yellow","gender":"man","size":"small"},
        {"cloth":"s","color":"pink","gender":"woman","size":"big"},
        {"cloth":"p","color":"yellow","gender":"man","size":"medium"},
        {"cloth":"t","color":"blue","gender":"woman","size":"small"},
        {"cloth":"t","color":"blue","gender":"man","size":"small"},
        {"cloth":"p","color":"yellow","gender":"woman","size":"medium"},
        {"cloth":"s","color":"pink","gender":"man","size":"big"},
        {"cloth":"s","color":"pink","gender":"woman","size":"big"},
        {"cloth":"t","color":"blue","gender":"man","size":"big"},
        {"cloth":"p","color":"yellow","gender":"woman","size":"medium"},
        {"cloth":"p","color":"blue","gender":"woman","size":"small"},
        {"cloth":"t","color":"yellow","gender":"man","size":"big"},
        {"cloth":"s","color":"blue","gender":"woman","size":"medium"},
        {"cloth":"t","color":"yellow","gender":"woman","size":"big"},
        {"cloth":"p","color":"pink","gender":"man","size":"small"},
        {"cloth":"p","color":"blue","gender":"woman","size":"medium"},
        {"cloth":"s","color":"pink","gender":"woman","size":"medium"},
        {"cloth":"t","color":"yellow","gender":"man","size":"small"},
        {"cloth":"t","color":"blue","gender":"woman","size":"big"},
        {"cloth":"s","color":"pink","gender":"woman","size":"big"},
        {"cloth":"p","color":"yellow","gender":"man","size":"small"},
        {"cloth":"s","color":"pink","gender":"woman","size":"medium"},
        {"cloth":"p","color":"yellow","gender":"woman","size":"big"},
        {"cloth":"t","color":"blue","gender":"woman","size":"small"},
        {"cloth":"t","color":"blue","gender":"woman","size":"medium"},
        {"cloth":"p","color":"yellow","gender":"man","size":"small"},
        {"cloth":"s","color":"pink","gender":"woman","size":"big"},
        {"cloth":"s","color":"pink","gender":"woman","size":"small"},
        {"cloth":"t","color":"blue","gender":"man","size":"big"},
        {"cloth":"p","color":"yellow","gender":"woman","size":"small"},
        {"cloth":"p","color":"blue","gender":"man","size":"big"},
        {"cloth":"t","color":"yellow","gender":"woman","size":"medium"},
        {"cloth":"s","color":"blue","gender":"woman","size":"small"},
        {"cloth":"t","color":"yellow","gender":"man","size":"big"},
        {"cloth":"p","color":"pink","gender":"man","size":"small"},
        {"cloth":"p","color":"blue","gender":"woman","size":"medium"},
        {"cloth":"s","color":"pink","gender":"man","size":"small"},
        {"cloth":"s","color":"pink","gender":"woman","size":"big"},
        {"cloth":"p","color":"yellow","gender":"man","size":"small"},
        {"cloth":"s","color":"pink","gender":"woman","size":"medium"},
        {"cloth":"p","color":"yellow","gender":"woman","size":"big"},
        {"cloth":"t","color":"blue","gender":"man","size":"big"},
        {"cloth":"s","color":"pink","gender":"woman","size":"big"},
        {"cloth":"p","color":"yellow","gender":"man","size":"small"},
        {"cloth":"p","color":"pink","gender":"man","size":"small"},
        {"cloth":"p","color":"blue","gender":"woman","size":"medium"},
        {"cloth":"s","color":"pink","gender":"woman","size":"medium"},
        {"cloth":"t","color":"yellow","gender":"man","size":"small"},
        {"cloth":"p","color":"blue","gender":"man","size":"small"},
        {"cloth":"t","color":"yellow","gender":"woman","size":"big"},
        {"cloth":"s","color":"blue","gender":"man","size":"small"},
        {"cloth":"t","color":"yellow","gender":"woman","size":"medium"}

        
]
}